harlequin_risingwave/__init__.py
harlequin_risingwave/adapter.py
harlequin_risingwave/completion.py
harlequin_risingwave-0.5.0.dist-info/LICENSE
harlequin_risingwave-0.5.0.dist-info/METADATA
harlequin_risingwave-0.5.0.dist-info/WHEEL
harlequin_risingwave-0.5.0.dist-info/entry_points.txt
harlequin_risingwave-0.5.0.dist-info/RECORD
